LICENSE
MANIFEST.in
README.rst
setup.cfg
setup.py
gdg/__init__.py
gdg/gdg.py
gdg/gdg_constants.py
gdg.egg-info/PKG-INFO
gdg.egg-info/SOURCES.txt
gdg.egg-info/dependency_links.txt
gdg.egg-info/requires.txt
gdg.egg-info/top_level.txt
tests/__init__.py
tests/test_epoch_type.py
tests/test_gdg_constants.py
tests/test_generation_type.py
tests/test_timestype_local_type.py
tests/test_timestype_utc_type.py